qlik_test_aviad/__init__.py
qlik_test_aviad-0.1.1.dist-info/METADATA
qlik_test_aviad-0.1.1.dist-info/WHEEL
qlik_test_aviad-0.1.1.dist-info/RECORD
