Metadata-Version: 2.1
Name: qlik-test-aviad
Version: 0.1.1
Summary: 
Author: Aviad Rozenhek
Author-email: aviadr1@gmail.com
Requires-Python: >=3.9,<4.0
Classifier: Programming Language :: Python :: 3
Classifier: Programming Language :: Python :: 3.9
Classifier: Programming Language :: Python :: 3.10
Classifier: Programming Language :: Python :: 3.11
Requires-Dist: pandas (>=1.4,<2.0)
